{"cameraMode":{"drawMode":0,"name":"Shaded","section":"Shading Mode"},"sceneLighting":true,"audioPlay":false,"sceneViewState":{"showFog":true,"showMaterialUpdate":false,"showSkybox":true,"showFlares":true,"showImageEffects":true,"showParticleSystems":true},"in2DMode":false,"pivot":{"x":582.3248901367188,"y":-1.0373053550720215,"z":156.34605407714845},"rotation":{"x":-0.05480453372001648,"y":0.9297376871109009,"z":-0.3297301232814789,"w":-0.15452611446380616},"size":3.198754072189331,"orthographic":false}